django_pyodbc/__init__.py
django_pyodbc/aggregates.py
django_pyodbc/base.py
django_pyodbc/client.py
django_pyodbc/compat.py
django_pyodbc/compiler.py
django_pyodbc/creation.py
django_pyodbc/introspection.py
django_pyodbc/metadata.py
django_pyodbc/operations.py
django_pyodbc/management/__init__.py
django_pyodbc/management/commands/__init__.py
django_pyodbc/management/commands/ss_loaddata.py
django_pyodbc-1.1.2.dist-info/DESCRIPTION.rst
django_pyodbc-1.1.2.dist-info/METADATA
django_pyodbc-1.1.2.dist-info/RECORD
django_pyodbc-1.1.2.dist-info/WHEEL
django_pyodbc-1.1.2.dist-info/metadata.json
django_pyodbc-1.1.2.dist-info/top_level.txt
