Metadata-Version: 2.0
Name: django-pyodbc
Version: 1.1.2
Summary: Django 1.5-1.10 SQL Server backend using pyodbc.
Home-page: https://github.com/lionheart/django-pyodbc
Author: Dan Loewenherz
Author-email: dan@lionheartsw.com
License: BSD 3-Clause License
Platform: UNKNOWN
Requires-Dist: pyodbc (<4.1,>=3.0.6)
